{"tasks":[{"id":"af8d079f-6b64-4f56-af49-2cc6bc9b31b1","title":"Task 01","description":"Descrição da Task 01","completed_at":null,"created_at":"Mon Sep 16 2024 12:39:43 GMT-0300 (Horário Padrão de Brasília)","update_at":"Mon Sep 16 2024 12:39:43 GMT-0300 (Horário Padrão de Brasília)"},{"id":"51ba5c09-3b94-4c16-86b1-a48a9a396a4f","title":"Task 02","description":"Descrição da Task 02","completed_at":null,"created_at":"Mon Sep 16 2024 12:39:43 GMT-0300 (Horário Padrão de Brasília)","update_at":"Mon Sep 16 2024 12:39:43 GMT-0300 (Horário Padrão de Brasília)"},{"id":"13c5ce3e-1e3e-40c9-a084-97fc33723ac0","title":"Task 03","description":"Descrição da Task 03","completed_at":null,"created_at":"Mon Sep 16 2024 12:39:43 GMT-0300 (Horário Padrão de Brasília)","update_at":"Mon Sep 16 2024 12:39:43 GMT-0300 (Horário Padrão de Brasília)"},{"id":"4855fa9f-b6b1-48c0-bd0c-1477b1844695","title":"Task 04","description":"Descrição da Task 04","completed_at":null,"created_at":"Mon Sep 16 2024 12:39:43 GMT-0300 (Horário Padrão de Brasília)","update_at":"Mon Sep 16 2024 12:39:43 GMT-0300 (Horário Padrão de Brasília)"},{"id":"2a1eb493-0b48-4435-9361-f5e110721655","title":"Task 05","description":"Descrição da Task 05","completed_at":null,"created_at":"Mon Sep 16 2024 12:39:43 GMT-0300 (Horário Padrão de Brasília)","update_at":"Mon Sep 16 2024 12:39:43 GMT-0300 (Horário Padrão de Brasília)"}]}